setup.py
cj_distributions/Binomialdistribution.py
cj_distributions/Gaussiandistribution.py
cj_distributions/Generaldistribution.py
cj_distributions/__init__.py
cj_distributions.egg-info/PKG-INFO
cj_distributions.egg-info/SOURCES.txt
cj_distributions.egg-info/dependency_links.txt
cj_distributions.egg-info/not-zip-safe
cj_distributions.egg-info/top_level.txt